{
  "meta": {
    "data_version": "1.0.0",
    "created": "2015-05-01",
    "revision": 1
  },
  "info": {
    "balls_per_over": 6,
    "city": "Mumbai",
    "dates": [
      "2015-05-01"
    ],
    "event": {
      "match_number": 32,
      "name": "Indian Premier League"
    },
    "gender": "male",
    "match_type": "T20",
    "officials": {
      "match_referees": [
        "RS Mahanama"
      ],
      "reserve_umpires": [
        "Nitin Menon"
      ],
      "tv_umpires": [
        "CB Gaffaney"
      ],
      "umpires": [
        "HDPK Dharmasena",
        "CK Nandan"
      ]
    },
    "outcome": {
      "by": {
        "runs": 8
      },
      "winner": "Mumbai Indians"
    },
    "overs": 20,
    "player_of_match": [
      "AT Rayudu"
    ],
    "players": {
      "Mumbai Indians": [
        "LMP Simmons",
        "PA Patel",
        "UBT Chand",
        "RG Sharma",
        "AT Rayudu",
        "KA Pollard",
        "Harbhajan Singh",
        "J Suchith",
        "R Vinay Kumar",
        "MJ McClenaghan",
        "SL Malinga"
      ],
      "Rajasthan Royals": [
        "AM Rahane",
        "SR Watson",
        "SV Samson",
        "SPD Smith",
        "KK Nair",
        "STR Binny",
        "DJ Hooda",
        "TG Southee",
        "J Theron",
        "DS Kulkarni",
        "Ankit Sharma"
      ]
    },
    "registry": {
      "people": {
        "AM Rahane": "29e95537",
        "AT Rayudu": "70d205c9",
        "Ankit Sharma": "24d94623",
        "CB Gaffaney": "d5ac41d8",
        "CK Nandan": "012de9c4",
        "DJ Hooda": "73ad96ed",
        "DS Kulkarni": "d2a989fc",
        "HDPK Dharmasena": "323e4c16",
        "Harbhajan Singh": "8b5b6769",
        "J Suchith": "4125d931",
        "J Theron": "dec8e038",
        "KA Pollard": "a757b0d8",
        "KK Nair": "944533a5",
        "LMP Simmons": "89f64c19",
        "MJ McClenaghan": "51a3c5ef",
        "Nitin Menon": "e1d41d9e",
        "PA Patel": "b5da6c24",
        "R Vinay Kumar": "41eb4a4f",
        "RG Sharma": "740742ef",
        "RS Mahanama": "57910393",
        "SL Malinga": "a12e1d51",
        "SPD Smith": "30a45b23",
        "SR Watson": "4329fbb5",
        "STR Binny": "bd17b45f",
        "SV Samson": "a4cc73aa",
        "TG Southee": "13c35c9e",
        "UBT Chand": "0c94f480"
      }
    },
    "season": 2015,
    "team_type": "club",
    "teams": [
      "Mumbai Indians",
      "Rajasthan Royals"
    ],
    "toss": {
      "decision": "field",
      "winner": "Rajasthan Royals"
    },
    "venue": "Wankhede Stadium"
  },
  "innings": [
    {
      "team": "Mumbai Indians",
      "overs": [
        {
          "over": 0,
          "deliveries": [
            {
              "batter": "LMP Simmons",
              "bowler": "TG Southee",
              "non_striker": "PA Patel",
              "runs": {
                "batter": 0,
                "extras": 0,
                "total": 0
              }
            },
            {
              "batter": "LMP Simmons",
              "bowler": "TG Southee",
              "non_striker": "PA Patel",
              "runs": {
                "batter": 0,
                "extras": 0,
                "total": 0
              }
            },
            {
              "batter": "LMP Simmons",
              "bowler": "TG Southee",
              "non_striker": "PA Patel",
              "runs": {
                "batter": 0,
                "extras": 0,
                "total": 0
              }
            },
            {
              "batter": "LMP Simmons",
              "bowler": "TG Southee",
              "non_striker": "PA Patel",
              "runs": {
                "batter": 4,
                "extras": 0,
                "total": 4
              }
            },
            {
              "batter": "LMP Simmons",
              "bowler": "TG Southee",
              "non_striker": "PA Patel",
              "runs": {
                "batter": 1,
                "extras": 0,
                "total": 1
              }
            },
            {
              "batter": "PA Patel",
              "bowler": "TG Southee",
              "non_striker": "LMP Simmons",
              "runs": {
                "batter": 0,
                "extras": 0,
                "total": 0
              }
            }
          ]
        },
        {
          "over": 1,
          "deliveries": [
            {
              "batter": "LMP Simmons",
              "bowler": "DS Kulkarni",
              "non_striker": "PA Patel",
              "runs": {
                "batter": 2,
                "extras": 0,
                "total": 2
              }
            },
            {
              "batter": "LMP Simmons",
              "bowler": "DS Kulkarni",
              "extras": {
                "wides": 2
              },
              "non_striker": "PA Patel",
              "runs": {
                "batter": 0,
                "extras": 2,
                "total": 2
              }
            },
            {
              "batter": "PA Patel",
              "bowler": "DS Kulkarni",
              "non_striker": "LMP Simmons",
              "runs": {
                "batter": 0,
                "extras": 0,
                "total": 0
              }
            },
            {
              "batter": "PA Patel",
              "bowler": "DS Kulkarni",
              "non_striker": "LMP Simmons",
              "runs": {
                "batter": 4,
                "extras": 0,
                "total": 4
              }
            },
            {
              "batter": "PA Patel",
              "bowler": "DS Kulkarni",
              "non_striker": "LMP Simmons",
              "runs": {
                "batter": 4,
                "extras": 0,
                "total": 4
              }
            },
            {
              "batter": "PA Patel",
              "bowler": "DS Kulkarni",
              "non_striker": "LMP Simmons",
              "runs": {
                "batter": 0,
                "extras": 0,
                "total": 0
              }
            },
            {
              "batter": "PA Patel",
              "bowler": "DS Kulkarni",
              "non_striker": "LMP Simmons",
              "runs": {
                "batter": 1,
                "extras": 0,
                "total": 1
              }
            }
          ]
        },
        {
          "over": 2,
          "deliveries": [
            {
              "batter": "PA Patel",
              "bowler": "TG Southee",
              "non_striker": "LMP Simmons",
              "runs": {
                "batter": 1,
                "extras": 0,
                "total": 1
              }
            },
            {
              "batter": "LMP Simmons",
              "bowler": "TG Southee",
              "non_striker": "PA Patel",
              "runs": {
                "batter": 2,
                "extras": 0,
                "total": 2
              }
            },
            {
              "batter": "LMP Simmons",
              "bowler": "TG Southee",
              "non_striker": "PA Patel",
              "runs": {
                "batter": 0,
                "extras": 0,
                "total": 0
              }
            },
            {
              "batter": "LMP Simmons",
              "bowler": "TG Southee",
              "non_striker": "PA Patel",
              "runs": {
                "batter": 1,
                "extras": 0,
                "total": 1
              }
            },
            {
              "batter": "PA Patel",
              "bowler": "TG Southee",
              "non_striker": "LMP Simmons",
              "runs": {
                "batter": 0,
                "extras": 0,
                "total": 0
              }
            },
            {
              "batter": "PA Patel",
              "bowler": "TG Southee",
              "non_striker": "LMP Simmons",
              "runs": {
                "batter": 4,
                "extras": 0,
                "total": 4
              }
            }
          ]
        },
        {
          "over": 3,
          "deliveries": [
            {
              "batter": "LMP Simmons",
              "bowler": "J Theron",
              "non_striker": "PA Patel",
              "runs": {
                "batter": 1,
                "extras": 0,
                "total": 1
              }
            },
            {
              "batter": "PA Patel",
              "bowler": "J Theron",
              "non_striker": "LMP Simmons",
              "runs": {
                "batter": 4,
                "extras": 0,
                "total": 4
              }
            },
            {
              "batter": "PA Patel",
              "bowler": "J Theron",
              "non_striker": "LMP Simmons",
              "runs": {
                "batter": 0,
                "extras": 0,
                "total": 0
              }
            },
            {
              "batter": "PA Patel",
              "bowler": "J Theron",
              "non_striker": "LMP Simmons",
              "runs": {
                "batter": 4,
                "extras": 0,
                "total": 4
              }
            },
            {
              "batter": "PA Patel",
              "bowler": "J Theron",
              "non_striker": "LMP Simmons",
              "runs": {
                "batter": 1,
                "extras": 0,
                "total": 1
              }
            },
            {
              "batter": "LMP Simmons",
              "bowler": "J Theron",
              "extras": {
                "wides": 1
              },
              "non_striker": "PA Patel",
              "runs": {
                "batter": 0,
                "extras": 1,
                "total": 1
              }
            },
            {
              "batter": "LMP Simmons",
              "bowler": "J Theron",
              "non_striker": "PA Patel",
              "runs": {
                "batter": 1,
                "extras": 0,
                "total": 1
              }
            }
          ]
        },
        {
          "over": 4,
          "deliveries": [
            {
              "batter": "LMP Simmons",
              "bowler": "DS Kulkarni",
              "non_striker": "PA Patel",
              "runs": {
                "batter": 0,
                "extras": 0,
                "total": 0
              }
            },
            {
              "batter": "LMP Simmons",
              "bowler": "DS Kulkarni",
              "non_striker": "PA Patel",
              "runs": {
                "batter": 4,
                "extras": 0,
                "total": 4
              }
            },
            {
              "batter": "LMP Simmons",
              "bowler": "DS Kulkarni",
              "non_striker": "PA Patel",
              "runs": {
                "batter": 0,
                "extras": 0,
                "total": 0
              }
            },
            {
              "batter": "LMP Simmons",
              "bowler": "DS Kulkarni",
              "non_striker": "PA Patel",
              "runs": {
                "batter": 1,
                "extras": 0,
                "total": 1
              }
            },
            {
              "batter": "PA Patel",
              "bowler": "DS Kulkarni",
              "non_striker": "LMP Simmons",
              "runs": {
                "batter": 0,
                "extras": 0,
                "total": 0
              },
              "wickets": [
                {
                  "kind": "caught and bowled",
                  "player_out": "PA Patel"
                }
              ]
            },
            {
              "batter": "UBT Chand",
              "bowler": "DS Kulkarni",
              "non_striker": "LMP Simmons",
              "runs": {
                "batter": 0,
                "extras": 0,
                "total": 0
              }
            }
          ]
        },
        {
          "over": 5,
          "deliveries": [
            {
              "batter": "LMP Simmons",
              "bowler": "SR Watson",
              "non_striker": "UBT Chand",
              "runs": {
                "batter": 1,
                "extras": 0,
                "total": 1
              }
            },
            {
              "batter": "UBT Chand",
              "bowler": "SR Watson",
              "non_striker": "LMP Simmons",
              "runs": {
                "batter": 0,
                "extras": 0,
                "total": 0
              }
            },
            {
              "batter": "UBT Chand",
              "bowler": "SR Watson",
              "non_striker": "LMP Simmons",
              "runs": {
                "batter": 1,
                "extras": 0,
                "total": 1
              }
            },
            {
              "batter": "LMP Simmons",
              "bowler": "SR Watson",
              "extras": {
                "legbyes": 1
              },
              "non_striker": "UBT Chand",
              "runs": {
                "batter": 0,
                "extras": 1,
                "total": 1
              }
            },
            {
              "batter": "UBT Chand",
              "bowler": "SR Watson",
              "non_striker": "LMP Simmons",
              "runs": {
                "batter": 0,
                "extras": 0,
                "total": 0
              }
            },
            {
              "batter": "UBT Chand",
              "bowler": "SR Watson",
              "non_striker": "LMP Simmons",
              "runs": {
                "batter": 1,
                "extras": 0,
                "total": 1
              }
            }
          ]
        },
        {
          "over": 6,
          "deliveries": [
            {
              "batter": "UBT Chand",
              "bowler": "STR Binny",
              "non_striker": "LMP Simmons",
              "runs": {
                "batter": 1,
                "extras": 0,
                "total": 1
              }
            },
            {
              "batter": "LMP Simmons",
              "bowler": "STR Binny",
              "non_striker": "UBT Chand",
              "runs": {
                "batter": 1,
                "extras": 0,
                "total": 1
              }
            },
            {
              "batter": "UBT Chand",
              "bowler": "STR Binny",
              "non_striker": "LMP Simmons",
              "runs": {
                "batter": 1,
                "extras": 0,
                "total": 1
              }
            },
            {
              "batter": "LMP Simmons",
              "bowler": "STR Binny",
              "non_striker": "UBT Chand",
              "runs": {
                "batter": 1,
                "extras": 0,
                "total": 1
              }
            },
            {
              "batter": "UBT Chand",
              "bowler": "STR Binny",
              "non_striker": "LMP Simmons",
              "runs": {
                "batter": 1,
                "extras": 0,
                "total": 1
              }
            },
            {
              "batter": "LMP Simmons",
              "bowler": "STR Binny",
              "non_striker": "UBT Chand",
              "runs": {
                "batter": 0,
                "extras": 0,
                "total": 0
              }
            }
          ]
        },
        {
          "over": 7,
          "deliveries": [
            {
              "batter": "UBT Chand",
              "bowler": "Ankit Sharma",
              "non_striker": "LMP Simmons",
              "runs": {
                "batter": 1,
                "extras": 0,
                "total": 1
              }
            },
            {
              "batter": "LMP Simmons",
              "bowler": "Ankit Sharma",
              "non_striker": "UBT Chand",
              "runs": {
                "batter": 0,
                "extras": 0,
                "total": 0
              }
            },
            {
              "batter": "LMP Simmons",
              "bowler": "Ankit Sharma",
              "non_striker": "UBT Chand",
              "runs": {
                "batter": 0,
                "extras": 0,
                "total": 0
              }
            },
            {
              "batter": "LMP Simmons",
              "bowler": "Ankit Sharma",
              "non_striker": "UBT Chand",
              "runs": {
                "batter": 4,
                "extras": 0,
                "total": 4
              }
            },
            {
              "batter": "LMP Simmons",
              "bowler": "Ankit Sharma",
              "non_striker": "UBT Chand",
              "runs": {
                "batter": 2,
                "extras": 0,
                "total": 2
              }
            },
            {
              "batter": "LMP Simmons",
              "bowler": "Ankit Sharma",
              "non_striker": "UBT Chand",
              "runs": {
                "batter": 1,
                "extras": 0,
                "total": 1
              }
            }
          ]
        },
        {
          "over": 8,
          "deliveries": [
            {
              "batter": "LMP Simmons",
              "bowler": "SR Watson",
              "non_striker": "UBT Chand",
              "runs": {
                "batter": 0,
                "extras": 0,
                "total": 0
              }
            },
            {
              "batter": "LMP Simmons",
              "bowler": "SR Watson",
              "non_striker": "UBT Chand",
              "runs": {
                "batter": 0,
                "extras": 0,
                "total": 0
              }
            },
            {
              "batter": "LMP Simmons",
              "bowler": "SR Watson",
              "non_striker": "UBT Chand",
              "runs": {
                "batter": 4,
                "extras": 0,
                "total": 4
              }
            },
            {
              "batter": "LMP Simmons",
              "bowler": "SR Watson",
              "non_striker": "UBT Chand",
              "runs": {
                "batter": 6,
                "extras": 0,
                "total": 6
              }
            },
            {
              "batter": "LMP Simmons",
              "bowler": "SR Watson",
              "non_striker": "UBT Chand",
              "runs": {
                "batter": 1,
                "extras": 0,
                "total": 1
              }
            },
            {
              "batter": "UBT Chand",
              "bowler": "SR Watson",
              "non_striker": "LMP Simmons",
              "runs": {
                "batter": 2,
                "extras": 0,
                "total": 2
              }
            }
          ]
        },
        {
          "over": 9,
          "deliveries": [
            {
              "batter": "LMP Simmons",
              "bowler": "Ankit Sharma",
              "non_striker": "UBT Chand",
              "runs": {
                "batter": 0,
                "extras": 0,
                "total": 0
              },
              "wickets": [
                {
                  "kind": "lbw",
                  "player_out": "LMP Simmons"
                }
              ]
            },
            {
              "batter": "RG Sharma",
              "bowler": "Ankit Sharma",
              "non_striker": "UBT Chand",
              "runs": {
                "batter": 1,
                "extras": 0,
                "total": 1
              }
            },
            {
              "batter": "UBT Chand",
              "bowler": "Ankit Sharma",
              "non_striker": "RG Sharma",
              "runs": {
                "batter": 1,
                "extras": 0,
                "total": 1
              }
            },
            {
              "batter": "RG Sharma",
              "bowler": "Ankit Sharma",
              "non_striker": "UBT Chand",
              "runs": {
                "batter": 0,
                "extras": 0,
                "total": 0
              }
            },
            {
              "batter": "RG Sharma",
              "bowler": "Ankit Sharma",
              "extras": {
                "wides": 1
              },
              "non_striker": "UBT Chand",
              "runs": {
                "batter": 0,
                "extras": 1,
                "total": 1
              }
            },
            {
              "batter": "RG Sharma",
              "bowler": "Ankit Sharma",
              "non_striker": "UBT Chand",
              "runs": {
                "batter": 1,
                "extras": 0,
                "total": 1
              }
            },
            {
              "batter": "UBT Chand",
              "bowler": "Ankit Sharma",
              "non_striker": "RG Sharma",
              "runs": {
                "batter": 4,
                "extras": 0,
                "total": 4
              }
            }
          ]
        },
        {
          "over": 10,
          "deliveries": [
            {
              "batter": "RG Sharma",
              "bowler": "TG Southee",
              "non_striker": "UBT Chand",
              "runs": {
                "batter": 2,
                "extras": 0,
                "total": 2
              }
            },
            {
              "batter": "RG Sharma",
              "bowler": "TG Southee",
              "non_striker": "UBT Chand",
              "runs": {
                "batter": 1,
                "extras": 0,
                "total": 1
              }
            },
            {
              "batter": "UBT Chand",
              "bowler": "TG Southee",
              "non_striker": "RG Sharma",
              "runs": {
                "batter": 0,
                "extras": 0,
                "total": 0
              }
            },
            {
              "batter": "UBT Chand",
              "bowler": "TG Southee",
              "non_striker": "RG Sharma",
              "runs": {
                "batter": 0,
                "extras": 0,
                "total": 0
              },
              "wickets": [
                {
                  "kind": "caught",
                  "player_out": "UBT Chand",
                  "fielders": [
                    {
                      "name": "STR Binny"
                    }
                  ]
                }
              ]
            },
            {
              "batter": "RG Sharma",
              "bowler": "TG Southee",
              "non_striker": "AT Rayudu",
              "runs": {
                "batter": 4,
                "extras": 0,
                "total": 4
              }
            },
            {
              "batter": "RG Sharma",
              "bowler": "TG Southee",
              "non_striker": "AT Rayudu",
              "runs": {
                "batter": 0,
                "extras": 0,
                "total": 0
              }
            }
          ]
        },
        {
          "over": 11,
          "deliveries": [
            {
              "batter": "AT Rayudu",
              "bowler": "Ankit Sharma",
              "non_striker": "RG Sharma",
              "runs": {
                "batter": 1,
                "extras": 0,
                "total": 1
              }
            },
            {
              "batter": "RG Sharma",
              "bowler": "Ankit Sharma",
              "non_striker": "AT Rayudu",
              "runs": {
                "batter": 2,
                "extras": 0,
                "total": 2
              }
            },
            {
              "batter": "RG Sharma",
              "bowler": "Ankit Sharma",
              "non_striker": "AT Rayudu",
              "runs": {
                "batter": 1,
                "extras": 0,
                "total": 1
              }
            },
            {
              "batter": "AT Rayudu",
              "bowler": "Ankit Sharma",
              "non_striker": "RG Sharma",
              "runs": {
                "batter": 1,
                "extras": 0,
                "total": 1
              }
            },
            {
              "batter": "RG Sharma",
              "bowler": "Ankit Sharma",
              "non_striker": "AT Rayudu",
              "runs": {
                "batter": 1,
                "extras": 0,
                "total": 1
              }
            },
            {
              "batter": "AT Rayudu",
              "bowler": "Ankit Sharma",
              "non_striker": "RG Sharma",
              "runs": {
                "batter": 1,
                "extras": 0,
                "total": 1
              }
            }
          ]
        },
        {
          "over": 12,
          "deliveries": [
            {
              "batter": "AT Rayudu",
              "bowler": "J Theron",
              "non_striker": "RG Sharma",
              "runs": {
                "batter": 1,
                "extras": 0,
                "total": 1
              }
            },
            {
              "batter": "RG Sharma",
              "bowler": "J Theron",
              "non_striker": "AT Rayudu",
              "runs": {
                "batter": 1,
                "extras": 0,
                "total": 1
              }
            },
            {
              "batter": "AT Rayudu",
              "bowler": "J Theron",
              "non_striker": "RG Sharma",
              "runs": {
                "batter": 1,
                "extras": 0,
                "total": 1
              }
            },
            {
              "batter": "RG Sharma",
              "bowler": "J Theron",
              "non_striker": "AT Rayudu",
              "runs": {
                "batter": 0,
                "extras": 0,
                "total": 0
              }
            },
            {
              "batter": "RG Sharma",
              "bowler": "J Theron",
              "non_striker": "AT Rayudu",
              "runs": {
                "batter": 1,
                "extras": 0,
                "total": 1
              }
            },
            {
              "batter": "AT Rayudu",
              "bowler": "J Theron",
              "non_striker": "RG Sharma",
              "runs": {
                "batter": 0,
                "extras": 0,
                "total": 0
              }
            }
          ]
        },
        {
          "over": 13,
          "deliveries": [
            {
              "batter": "RG Sharma",
              "bowler": "STR Binny",
              "non_striker": "AT Rayudu",
              "runs": {
                "batter": 1,
                "extras": 0,
                "total": 1
              }
            },
            {
              "batter": "AT Rayudu",
              "bowler": "STR Binny",
              "non_striker": "RG Sharma",
              "runs": {
                "batter": 1,
                "extras": 0,
                "total": 1
              }
            },
            {
              "batter": "RG Sharma",
              "bowler": "STR Binny",
              "non_striker": "AT Rayudu",
              "runs": {
                "batter": 4,
                "extras": 0,
                "total": 4
              }
            },
            {
              "batter": "RG Sharma",
              "bowler": "STR Binny",
              "non_striker": "AT Rayudu",
              "runs": {
                "batter": 0,
                "extras": 0,
                "total": 0
              }
            },
            {
              "batter": "RG Sharma",
              "bowler": "STR Binny",
              "extras": {
                "legbyes": 1
              },
              "non_striker": "AT Rayudu",
              "runs": {
                "batter": 0,
                "extras": 1,
                "total": 1
              }
            },
            {
              "batter": "AT Rayudu",
              "bowler": "STR Binny",
              "non_striker": "RG Sharma",
              "runs": {
                "batter": 6,
                "extras": 0,
                "total": 6
              }
            }
          ]
        },
        {
          "over": 14,
          "deliveries": [
            {
              "batter": "RG Sharma",
              "bowler": "DS Kulkarni",
              "non_striker": "AT Rayudu",
              "runs": {
                "batter": 0,
                "extras": 0,
                "total": 0
              }
            },
            {
              "batter": "RG Sharma",
              "bowler": "DS Kulkarni",
              "non_striker": "AT Rayudu",
              "runs": {
                "batter": 1,
                "extras": 0,
                "total": 1
              }
            },
            {
              "batter": "AT Rayudu",
              "bowler": "DS Kulkarni",
              "non_striker": "RG Sharma",
              "runs": {
                "batter": 1,
                "extras": 0,
                "total": 1
              }
            },
            {
              "batter": "RG Sharma",
              "bowler": "DS Kulkarni",
              "non_striker": "AT Rayudu",
              "runs": {
                "batter": 6,
                "extras": 0,
                "total": 6
              }
            },
            {
              "batter": "RG Sharma",
              "bowler": "DS Kulkarni",
              "non_striker": "AT Rayudu",
              "runs": {
                "batter": 0,
                "extras": 0,
                "total": 0
              },
              "wickets": [
                {
                  "kind": "caught",
                  "player_out": "RG Sharma",
                  "fielders": [
                    {
                      "name": "Ankit Sharma"
                    }
                  ]
                }
              ]
            },
            {
              "batter": "KA Pollard",
              "bowler": "DS Kulkarni",
              "non_striker": "AT Rayudu",
              "runs": {
                "batter": 0,
                "extras": 0,
                "total": 0
              }
            }
          ]
        },
        {
          "over": 15,
          "deliveries": [
            {
              "batter": "AT Rayudu",
              "bowler": "Ankit Sharma",
              "non_striker": "KA Pollard",
              "runs": {
                "batter": 1,
                "extras": 0,
                "total": 1
              }
            },
            {
              "batter": "KA Pollard",
              "bowler": "Ankit Sharma",
              "non_striker": "AT Rayudu",
              "runs": {
                "batter": 1,
                "extras": 0,
                "total": 1
              }
            },
            {
              "batter": "AT Rayudu",
              "bowler": "Ankit Sharma",
              "non_striker": "KA Pollard",
              "runs": {
                "batter": 1,
                "extras": 0,
                "total": 1
              }
            },
            {
              "batter": "KA Pollard",
              "bowler": "Ankit Sharma",
              "non_striker": "AT Rayudu",
              "runs": {
                "batter": 1,
                "extras": 0,
                "total": 1
              }
            },
            {
              "batter": "AT Rayudu",
              "bowler": "Ankit Sharma",
              "non_striker": "KA Pollard",
              "runs": {
                "batter": 0,
                "extras": 0,
                "total": 0
              }
            },
            {
              "batter": "AT Rayudu",
              "bowler": "Ankit Sharma",
              "non_striker": "KA Pollard",
              "runs": {
                "batter": 2,
                "extras": 0,
                "total": 2
              }
            }
          ]
        },
        {
          "over": 16,
          "deliveries": [
            {
              "batter": "KA Pollard",
              "bowler": "J Theron",
              "extras": {
                "legbyes": 1
              },
              "non_striker": "AT Rayudu",
              "runs": {
                "batter": 0,
                "extras": 1,
                "total": 1
              }
            },
            {
              "batter": "AT Rayudu",
              "bowler": "J Theron",
              "non_striker": "KA Pollard",
              "runs": {
                "batter": 1,
                "extras": 0,
                "total": 1
              }
            },
            {
              "batter": "KA Pollard",
              "bowler": "J Theron",
              "extras": {
                "wides": 1
              },
              "non_striker": "AT Rayudu",
              "runs": {
                "batter": 0,
                "extras": 1,
                "total": 1
              }
            },
            {
              "batter": "KA Pollard",
              "bowler": "J Theron",
              "non_striker": "AT Rayudu",
              "runs": {
                "batter": 2,
                "extras": 0,
                "total": 2
              }
            },
            {
              "batter": "KA Pollard",
              "bowler": "J Theron",
              "non_striker": "AT Rayudu",
              "runs": {
                "batter": 1,
                "extras": 0,
                "total": 1
              }
            },
            {
              "batter": "AT Rayudu",
              "bowler": "J Theron",
              "non_striker": "KA Pollard",
              "runs": {
                "batter": 6,
                "extras": 0,
                "total": 6
              }
            },
            {
              "batter": "AT Rayudu",
              "bowler": "J Theron",
              "non_striker": "KA Pollard",
              "runs": {
                "batter": 1,
                "extras": 0,
                "total": 1
              }
            }
          ]
        },
        {
          "over": 17,
          "deliveries": [
            {
              "batter": "AT Rayudu",
              "bowler": "SR Watson",
              "non_striker": "KA Pollard",
              "runs": {
                "batter": 4,
                "extras": 0,
                "total": 4
              }
            },
            {
              "batter": "AT Rayudu",
              "bowler": "SR Watson",
              "non_striker": "KA Pollard",
              "runs": {
                "batter": 1,
                "extras": 0,
                "total": 1
              }
            },
            {
              "batter": "KA Pollard",
              "bowler": "SR Watson",
              "non_striker": "AT Rayudu",
              "runs": {
                "batter": 1,
                "extras": 0,
                "total": 1
              }
            },
            {
              "batter": "AT Rayudu",
              "bowler": "SR Watson",
              "non_striker": "KA Pollard",
              "runs": {
                "batter": 1,
                "extras": 0,
                "total": 1
              }
            },
            {
              "batter": "KA Pollard",
              "bowler": "SR Watson",
              "non_striker": "AT Rayudu",
              "runs": {
                "batter": 6,
                "extras": 0,
                "total": 6
              }
            },
            {
              "batter": "KA Pollard",
              "bowler": "SR Watson",
              "extras": {
                "noballs": 1
              },
              "non_striker": "AT Rayudu",
              "runs": {
                "batter": 4,
                "extras": 1,
                "total": 5
              }
            },
            {
              "batter": "KA Pollard",
              "bowler": "SR Watson",
              "non_striker": "AT Rayudu",
              "runs": {
                "batter": 2,
                "extras": 0,
                "total": 2
              }
            }
          ]
        },
        {
          "over": 18,
          "deliveries": [
            {
              "batter": "AT Rayudu",
              "bowler": "TG Southee",
              "non_striker": "KA Pollard",
              "runs": {
                "batter": 0,
                "extras": 0,
                "total": 0
              }
            },
            {
              "batter": "AT Rayudu",
              "bowler": "TG Southee",
              "non_striker": "KA Pollard",
              "runs": {
                "batter": 4,
                "extras": 0,
                "total": 4
              }
            },
            {
              "batter": "AT Rayudu",
              "bowler": "TG Southee",
              "non_striker": "KA Pollard",
              "runs": {
                "batter": 1,
                "extras": 0,
                "total": 1
              }
            },
            {
              "batter": "KA Pollard",
              "bowler": "TG Southee",
              "non_striker": "AT Rayudu",
              "runs": {
                "batter": 1,
                "extras": 0,
                "total": 1
              }
            },
            {
              "batter": "AT Rayudu",
              "bowler": "TG Southee",
              "non_striker": "KA Pollard",
              "runs": {
                "batter": 6,
                "extras": 0,
                "total": 6
              }
            },
            {
              "batter": "AT Rayudu",
              "bowler": "TG Southee",
              "non_striker": "KA Pollard",
              "runs": {
                "batter": 4,
                "extras": 0,
                "total": 4
              }
            }
          ]
        },
        {
          "over": 19,
          "deliveries": [
            {
              "batter": "KA Pollard",
              "bowler": "J Theron",
              "non_striker": "AT Rayudu",
              "runs": {
                "batter": 1,
                "extras": 0,
                "total": 1
              }
            },
            {
              "batter": "AT Rayudu",
              "bowler": "J Theron",
              "non_striker": "KA Pollard",
              "runs": {
                "batter": 1,
                "extras": 0,
                "total": 1
              }
            },
            {
              "batter": "KA Pollard",
              "bowler": "J Theron",
              "non_striker": "AT Rayudu",
              "runs": {
                "batter": 4,
                "extras": 0,
                "total": 4
              }
            },
            {
              "batter": "KA Pollard",
              "bowler": "J Theron",
              "non_striker": "AT Rayudu",
              "runs": {
                "batter": 0,
                "extras": 0,
                "total": 0
              },
              "wickets": [
                {
                  "kind": "caught",
                  "player_out": "KA Pollard",
                  "fielders": [
                    {
                      "name": "SV Samson"
                    }
                  ]
                }
              ]
            },
            {
              "batter": "AT Rayudu",
              "bowler": "J Theron",
              "non_striker": "Harbhajan Singh",
              "runs": {
                "batter": 2,
                "extras": 0,
                "total": 2
              }
            },
            {
              "batter": "AT Rayudu",
              "bowler": "J Theron",
              "non_striker": "Harbhajan Singh",
              "runs": {
                "batter": 4,
                "extras": 0,
                "total": 4
              }
            }
          ]
        }
      ],
      "powerplays": [
        {
          "from": 0.1,
          "to": 5.6,
          "type": "mandatory"
        }
      ]
    },
    {
      "team": "Rajasthan Royals",
      "overs": [
        {
          "over": 0,
          "deliveries": [
            {
              "batter": "AM Rahane",
              "bowler": "MJ McClenaghan",
              "extras": {
                "wides": 1
              },
              "non_striker": "SR Watson",
              "runs": {
                "batter": 0,
                "extras": 1,
                "total": 1
              }
            },
            {
              "batter": "AM Rahane",
              "bowler": "MJ McClenaghan",
              "non_striker": "SR Watson",
              "runs": {
                "batter": 1,
                "extras": 0,
                "total": 1
              }
            },
            {
              "batter": "SR Watson",
              "bowler": "MJ McClenaghan",
              "non_striker": "AM Rahane",
              "runs": {
                "batter": 0,
                "extras": 0,
                "total": 0
              }
            },
            {
              "batter": "SR Watson",
              "bowler": "MJ McClenaghan",
              "non_striker": "AM Rahane",
              "runs": {
                "batter": 1,
                "extras": 0,
                "total": 1
              }
            },
            {
              "batter": "AM Rahane",
              "bowler": "MJ McClenaghan",
              "extras": {
                "wides": 1
              },
              "non_striker": "SR Watson",
              "runs": {
                "batter": 0,
                "extras": 1,
                "total": 1
              }
            },
            {
              "batter": "AM Rahane",
              "bowler": "MJ McClenaghan",
              "non_striker": "SR Watson",
              "runs": {
                "batter": 4,
                "extras": 0,
                "total": 4
              }
            },
            {
              "batter": "AM Rahane",
              "bowler": "MJ McClenaghan",
              "non_striker": "SR Watson",
              "runs": {
                "batter": 1,
                "extras": 0,
                "total": 1
              }
            },
            {
              "batter": "SR Watson",
              "bowler": "MJ McClenaghan",
              "non_striker": "AM Rahane",
              "runs": {
                "batter": 0,
                "extras": 0,
                "total": 0
              }
            }
          ]
        },
        {
          "over": 1,
          "deliveries": [
            {
              "batter": "AM Rahane",
              "bowler": "SL Malinga",
              "non_striker": "SR Watson",
              "runs": {
                "batter": 1,
                "extras": 0,
                "total": 1
              }
            },
            {
              "batter": "SR Watson",
              "bowler": "SL Malinga",
              "non_striker": "AM Rahane",
              "runs": {
                "batter": 1,
                "extras": 0,
                "total": 1
              }
            },
            {
              "batter": "AM Rahane",
              "bowler": "SL Malinga",
              "non_striker": "SR Watson",
              "runs": {
                "batter": 2,
                "extras": 0,
                "total": 2
              }
            },
            {
              "batter": "AM Rahane",
              "bowler": "SL Malinga",
              "non_striker": "SR Watson",
              "runs": {
                "batter": 0,
                "extras": 0,
                "total": 0
              }
            },
            {
              "batter": "AM Rahane",
              "bowler": "SL Malinga",
              "non_striker": "SR Watson",
              "runs": {
                "batter": 4,
                "extras": 0,
                "total": 4
              }
            },
            {
              "batter": "AM Rahane",
              "bowler": "SL Malinga",
              "non_striker": "SR Watson",
              "runs": {
                "batter": 1,
                "extras": 0,
                "total": 1
              }
            }
          ]
        },
        {
          "over": 2,
          "deliveries": [
            {
              "batter": "AM Rahane",
              "bowler": "MJ McClenaghan",
              "non_striker": "SR Watson",
              "runs": {
                "batter": 1,
                "extras": 0,
                "total": 1
              }
            },
            {
              "batter": "SR Watson",
              "bowler": "MJ McClenaghan",
              "non_striker": "AM Rahane",
              "runs": {
                "batter": 6,
                "extras": 0,
                "total": 6
              }
            },
            {
              "batter": "SR Watson",
              "bowler": "MJ McClenaghan",
              "extras": {
                "wides": 1
              },
              "non_striker": "AM Rahane",
              "runs": {
                "batter": 0,
                "extras": 1,
                "total": 1
              }
            },
            {
              "batter": "SR Watson",
              "bowler": "MJ McClenaghan",
              "non_striker": "AM Rahane",
              "runs": {
                "batter": 1,
                "extras": 0,
                "total": 1
              }
            },
            {
              "batter": "AM Rahane",
              "bowler": "MJ McClenaghan",
              "non_striker": "SR Watson",
              "runs": {
                "batter": 1,
                "extras": 0,
                "total": 1
              }
            },
            {
              "batter": "SR Watson",
              "bowler": "MJ McClenaghan",
              "non_striker": "AM Rahane",
              "runs": {
                "batter": 1,
                "extras": 0,
                "total": 1
              }
            },
            {
              "batter": "AM Rahane",
              "bowler": "MJ McClenaghan",
              "extras": {
                "legbyes": 1
              },
              "non_striker": "SR Watson",
              "runs": {
                "batter": 0,
                "extras": 1,
                "total": 1
              }
            }
          ]
        },
        {
          "over": 3,
          "deliveries": [
            {
              "batter": "AM Rahane",
              "bowler": "R Vinay Kumar",
              "non_striker": "SR Watson",
              "runs": {
                "batter": 0,
                "extras": 0,
                "total": 0
              },
              "wickets": [
                {
                  "kind": "caught",
                  "player_out": "AM Rahane",
                  "fielders": [
                    {
                      "name": "AT Rayudu"
                    }
                  ]
                }
              ]
            },
            {
              "batter": "SR Watson",
              "bowler": "R Vinay Kumar",
              "non_striker": "SV Samson",
              "runs": {
                "batter": 4,
                "extras": 0,
                "total": 4
              }
            },
            {
              "batter": "SR Watson",
              "bowler": "R Vinay Kumar",
              "non_striker": "SV Samson",
              "runs": {
                "batter": 0,
                "extras": 0,
                "total": 0
              }
            },
            {
              "batter": "SR Watson",
              "bowler": "R Vinay Kumar",
              "non_striker": "SV Samson",
              "runs": {
                "batter": 1,
                "extras": 0,
                "total": 1
              }
            },
            {
              "batter": "SV Samson",
              "bowler": "R Vinay Kumar",
              "non_striker": "SR Watson",
              "runs": {
                "batter": 0,
                "extras": 0,
                "total": 0
              }
            },
            {
              "batter": "SV Samson",
              "bowler": "R Vinay Kumar",
              "non_striker": "SR Watson",
              "runs": {
                "batter": 4,
                "extras": 0,
                "total": 4
              }
            }
          ]
        },
        {
          "over": 4,
          "deliveries": [
            {
              "batter": "SR Watson",
              "bowler": "J Suchith",
              "non_striker": "SV Samson",
              "runs": {
                "batter": 0,
                "extras": 0,
                "total": 0
              }
            },
            {
              "batter": "SR Watson",
              "bowler": "J Suchith",
              "non_striker": "SV Samson",
              "runs": {
                "batter": 0,
                "extras": 0,
                "total": 0
              }
            },
            {
              "batter": "SR Watson",
              "bowler": "J Suchith",
              "non_striker": "SV Samson",
              "runs": {
                "batter": 0,
                "extras": 0,
                "total": 0
              }
            },
            {
              "batter": "SR Watson",
              "bowler": "J Suchith",
              "non_striker": "SV Samson",
              "runs": {
                "batter": 0,
                "extras": 0,
                "total": 0
              }
            },
            {
              "batter": "SR Watson",
              "bowler": "J Suchith",
              "non_striker": "SV Samson",
              "runs": {
                "batter": 6,
                "extras": 0,
                "total": 6
              }
            },
            {
              "batter": "SR Watson",
              "bowler": "J Suchith",
              "non_striker": "SV Samson",
              "runs": {
                "batter": 4,
                "extras": 0,
                "total": 4
              }
            }
          ]
        },
        {
          "over": 5,
          "deliveries": [
            {
              "batter": "SV Samson",
              "bowler": "R Vinay Kumar",
              "non_striker": "SR Watson",
              "runs": {
                "batter": 4,
                "extras": 0,
                "total": 4
              }
            },
            {
              "batter": "SV Samson",
              "bowler": "R Vinay Kumar",
              "non_striker": "SR Watson",
              "runs": {
                "batter": 0,
                "extras": 0,
                "total": 0
              }
            },
            {
              "batter": "SV Samson",
              "bowler": "R Vinay Kumar",
              "non_striker": "SR Watson",
              "runs": {
                "batter": 0,
                "extras": 0,
                "total": 0
              }
            },
            {
              "batter": "SV Samson",
              "bowler": "R Vinay Kumar",
              "non_striker": "SR Watson",
              "runs": {
                "batter": 1,
                "extras": 0,
                "total": 1
              }
            },
            {
              "batter": "SR Watson",
              "bowler": "R Vinay Kumar",
              "non_striker": "SV Samson",
              "runs": {
                "batter": 1,
                "extras": 0,
                "total": 1
              }
            },
            {
              "batter": "SV Samson",
              "bowler": "R Vinay Kumar",
              "non_striker": "SR Watson",
              "runs": {
                "batter": 0,
                "extras": 0,
                "total": 0
              }
            }
          ]
        },
        {
          "over": 6,
          "deliveries": [
            {
              "batter": "SR Watson",
              "bowler": "J Suchith",
              "extras": {
                "wides": 3
              },
              "non_striker": "SV Samson",
              "runs": {
                "batter": 0,
                "extras": 3,
                "total": 3
              }
            },
            {
              "batter": "SR Watson",
              "bowler": "J Suchith",
              "non_striker": "SV Samson",
              "runs": {
                "batter": 0,
                "extras": 0,
                "total": 0
              }
            },
            {
              "batter": "SR Watson",
              "bowler": "J Suchith",
              "non_striker": "SV Samson",
              "runs": {
                "batter": 0,
                "extras": 0,
                "total": 0
              }
            },
            {
              "batter": "SR Watson",
              "bowler": "J Suchith",
              "non_striker": "SV Samson",
              "runs": {
                "batter": 1,
                "extras": 0,
                "total": 1
              }
            },
            {
              "batter": "SV Samson",
              "bowler": "J Suchith",
              "non_striker": "SR Watson",
              "runs": {
                "batter": 2,
                "extras": 0,
                "total": 2
              }
            },
            {
              "batter": "SV Samson",
              "bowler": "J Suchith",
              "non_striker": "SR Watson",
              "runs": {
                "batter": 1,
                "extras": 0,
                "total": 1
              }
            },
            {
              "batter": "SR Watson",
              "bowler": "J Suchith",
              "non_striker": "SV Samson",
              "runs": {
                "batter": 0,
                "extras": 0,
                "total": 0
              }
            }
          ]
        },
        {
          "over": 7,
          "deliveries": [
            {
              "batter": "SV Samson",
              "bowler": "Harbhajan Singh",
              "extras": {
                "wides": 1
              },
              "non_striker": "SR Watson",
              "runs": {
                "batter": 0,
                "extras": 1,
                "total": 1
              }
            },
            {
              "batter": "SV Samson",
              "bowler": "Harbhajan Singh",
              "non_striker": "SR Watson",
              "runs": {
                "batter": 0,
                "extras": 0,
                "total": 0
              }
            },
            {
              "batter": "SV Samson",
              "bowler": "Harbhajan Singh",
              "non_striker": "SR Watson",
              "runs": {
                "batter": 2,
                "extras": 0,
                "total": 2
              }
            },
            {
              "batter": "SV Samson",
              "bowler": "Harbhajan Singh",
              "non_striker": "SR Watson",
              "runs": {
                "batter": 0,
                "extras": 0,
                "total": 0
              }
            },
            {
              "batter": "SV Samson",
              "bowler": "Harbhajan Singh",
              "non_striker": "SR Watson",
              "runs": {
                "batter": 1,
                "extras": 0,
                "total": 1
              }
            },
            {
              "batter": "SR Watson",
              "bowler": "Harbhajan Singh",
              "non_striker": "SV Samson",
              "runs": {
                "batter": 1,
                "extras": 0,
                "total": 1
              }
            },
            {
              "batter": "SV Samson",
              "bowler": "Harbhajan Singh",
              "non_striker": "SR Watson",
              "runs": {
                "batter": 4,
                "extras": 0,
                "total": 4
              }
            }
          ]
        },
        {
          "over": 8,
          "deliveries": [
            {
              "batter": "SR Watson",
              "bowler": "J Suchith",
              "non_striker": "SV Samson",
              "runs": {
                "batter": 0,
                "extras": 0,
                "total": 0
              },
              "wickets": [
                {
                  "kind": "bowled",
                  "player_out": "SR Watson"
                }
              ]
            },
            {
              "batter": "SPD Smith",
              "bowler": "J Suchith",
              "non_striker": "SV Samson",
              "runs": {
                "batter": 1,
                "extras": 0,
                "total": 1
              }
            },
            {
              "batter": "SV Samson",
              "bowler": "J Suchith",
              "non_striker": "SPD Smith",
              "runs": {
                "batter": 3,
                "extras": 0,
                "total": 3
              }
            },
            {
              "batter": "SPD Smith",
              "bowler": "J Suchith",
              "extras": {
                "wides": 1
              },
              "non_striker": "SV Samson",
              "runs": {
                "batter": 0,
                "extras": 1,
                "total": 1
              }
            },
            {
              "batter": "SPD Smith",
              "bowler": "J Suchith",
              "non_striker": "SV Samson",
              "runs": {
                "batter": 1,
                "extras": 0,
                "total": 1
              }
            },
            {
              "batter": "SV Samson",
              "bowler": "J Suchith",
              "non_striker": "SPD Smith",
              "runs": {
                "batter": 1,
                "extras": 0,
                "total": 1
              }
            },
            {
              "batter": "SPD Smith",
              "bowler": "J Suchith",
              "non_striker": "SV Samson",
              "runs": {
                "batter": 4,
                "extras": 0,
                "total": 4
              }
            }
          ]
        },
        {
          "over": 9,
          "deliveries": [
            {
              "batter": "SV Samson",
              "bowler": "Harbhajan Singh",
              "non_striker": "SPD Smith",
              "runs": {
                "batter": 0,
                "extras": 0,
                "total": 0
              }
            },
            {
              "batter": "SV Samson",
              "bowler": "Harbhajan Singh",
              "non_striker": "SPD Smith",
              "runs": {
                "batter": 0,
                "extras": 0,
                "total": 0
              }
            },
            {
              "batter": "SV Samson",
              "bowler": "Harbhajan Singh",
              "non_striker": "SPD Smith",
              "runs": {
                "batter": 2,
                "extras": 0,
                "total": 2
              }
            },
            {
              "batter": "SV Samson",
              "bowler": "Harbhajan Singh",
              "non_striker": "SPD Smith",
              "runs": {
                "batter": 1,
                "extras": 0,
                "total": 1
              }
            },
            {
              "batter": "SPD Smith",
              "bowler": "Harbhajan Singh",
              "non_striker": "SV Samson",
              "runs": {
                "batter": 1,
                "extras": 0,
                "total": 1
              }
            },
            {
              "batter": "SV Samson",
              "bowler": "Harbhajan Singh",
              "non_striker": "SPD Smith",
              "runs": {
                "batter": 1,
                "extras": 0,
                "total": 1
              }
            }
          ]
        },
        {
          "over": 10,
          "deliveries": [
            {
              "batter": "SV Samson",
              "bowler": "J Suchith",
              "non_striker": "SPD Smith",
              "runs": {
                "batter": 1,
                "extras": 0,
                "total": 1
              }
            },
            {
              "batter": "SPD Smith",
              "bowler": "J Suchith",
              "non_striker": "SV Samson",
              "runs": {
                "batter": 1,
                "extras": 0,
                "total": 1
              }
            },
            {
              "batter": "SV Samson",
              "bowler": "J Suchith",
              "non_striker": "SPD Smith",
              "runs": {
                "batter": 6,
                "extras": 0,
                "total": 6
              }
            },
            {
              "batter": "SV Samson",
              "bowler": "J Suchith",
              "non_striker": "SPD Smith",
              "runs": {
                "batter": 1,
                "extras": 0,
                "total": 1
              }
            },
            {
              "batter": "SPD Smith",
              "bowler": "J Suchith",
              "non_striker": "SV Samson",
              "runs": {
                "batter": 1,
                "extras": 0,
                "total": 1
              }
            },
            {
              "batter": "SV Samson",
              "bowler": "J Suchith",
              "non_striker": "SPD Smith",
              "runs": {
                "batter": 1,
                "extras": 0,
                "total": 1
              }
            }
          ]
        },
        {
          "over": 11,
          "deliveries": [
            {
              "batter": "SV Samson",
              "bowler": "Harbhajan Singh",
              "non_striker": "SPD Smith",
              "runs": {
                "batter": 1,
                "extras": 0,
                "total": 1
              }
            },
            {
              "batter": "SPD Smith",
              "bowler": "Harbhajan Singh",
              "non_striker": "SV Samson",
              "runs": {
                "batter": 1,
                "extras": 0,
                "total": 1
              }
            },
            {
              "batter": "SV Samson",
              "bowler": "Harbhajan Singh",
              "non_striker": "SPD Smith",
              "runs": {
                "batter": 0,
                "extras": 0,
                "total": 0
              }
            },
            {
              "batter": "SV Samson",
              "bowler": "Harbhajan Singh",
              "non_striker": "SPD Smith",
              "runs": {
                "batter": 4,
                "extras": 0,
                "total": 4
              }
            },
            {
              "batter": "SV Samson",
              "bowler": "Harbhajan Singh",
              "non_striker": "SPD Smith",
              "runs": {
                "batter": 1,
                "extras": 0,
                "total": 1
              }
            },
            {
              "batter": "SPD Smith",
              "bowler": "Harbhajan Singh",
              "non_striker": "SV Samson",
              "runs": {
                "batter": 4,
                "extras": 0,
                "total": 4
              }
            }
          ]
        },
        {
          "over": 12,
          "deliveries": [
            {
              "batter": "SV Samson",
              "bowler": "SL Malinga",
              "non_striker": "SPD Smith",
              "runs": {
                "batter": 1,
                "extras": 0,
                "total": 1
              }
            },
            {
              "batter": "SPD Smith",
              "bowler": "SL Malinga",
              "non_striker": "SV Samson",
              "runs": {
                "batter": 2,
                "extras": 0,
                "total": 2
              }
            },
            {
              "batter": "SPD Smith",
              "bowler": "SL Malinga",
              "non_striker": "SV Samson",
              "runs": {
                "batter": 0,
                "extras": 0,
                "total": 0
              }
            },
            {
              "batter": "SPD Smith",
              "bowler": "SL Malinga",
              "non_striker": "SV Samson",
              "runs": {
                "batter": 1,
                "extras": 0,
                "total": 1
              }
            },
            {
              "batter": "SV Samson",
              "bowler": "SL Malinga",
              "non_striker": "SPD Smith",
              "runs": {
                "batter": 1,
                "extras": 0,
                "total": 1
              }
            },
            {
              "batter": "SPD Smith",
              "bowler": "SL Malinga",
              "non_striker": "SV Samson",
              "runs": {
                "batter": 1,
                "extras": 0,
                "total": 1
              }
            }
          ]
        },
        {
          "over": 13,
          "deliveries": [
            {
              "batter": "SPD Smith",
              "bowler": "Harbhajan Singh",
              "non_striker": "SV Samson",
              "runs": {
                "batter": 1,
                "extras": 0,
                "total": 1
              }
            },
            {
              "batter": "SV Samson",
              "bowler": "Harbhajan Singh",
              "non_striker": "SPD Smith",
              "runs": {
                "batter": 0,
                "extras": 0,
                "total": 0
              }
            },
            {
              "batter": "SV Samson",
              "bowler": "Harbhajan Singh",
              "non_striker": "SPD Smith",
              "runs": {
                "batter": 1,
                "extras": 0,
                "total": 1
              }
            },
            {
              "batter": "SPD Smith",
              "bowler": "Harbhajan Singh",
              "non_striker": "SV Samson",
              "runs": {
                "batter": 2,
                "extras": 0,
                "total": 2
              }
            },
            {
              "batter": "SPD Smith",
              "bowler": "Harbhajan Singh",
              "non_striker": "SV Samson",
              "runs": {
                "batter": 1,
                "extras": 0,
                "total": 1
              }
            },
            {
              "batter": "SV Samson",
              "bowler": "Harbhajan Singh",
              "non_striker": "SPD Smith",
              "runs": {
                "batter": 4,
                "extras": 0,
                "total": 4
              }
            }
          ]
        },
        {
          "over": 14,
          "deliveries": [
            {
              "batter": "SPD Smith",
              "bowler": "MJ McClenaghan",
              "extras": {
                "wides": 1
              },
              "non_striker": "SV Samson",
              "runs": {
                "batter": 0,
                "extras": 1,
                "total": 1
              }
            },
            {
              "batter": "SPD Smith",
              "bowler": "MJ McClenaghan",
              "non_striker": "SV Samson",
              "runs": {
                "batter": 0,
                "extras": 0,
                "total": 0
              }
            },
            {
              "batter": "SPD Smith",
              "bowler": "MJ McClenaghan",
              "non_striker": "SV Samson",
              "runs": {
                "batter": 0,
                "extras": 0,
                "total": 0
              }
            },
            {
              "batter": "SPD Smith",
              "bowler": "MJ McClenaghan",
              "non_striker": "SV Samson",
              "runs": {
                "batter": 0,
                "extras": 0,
                "total": 0
              }
            },
            {
              "batter": "SPD Smith",
              "bowler": "MJ McClenaghan",
              "non_striker": "SV Samson",
              "runs": {
                "batter": 1,
                "extras": 0,
                "total": 1
              }
            },
            {
              "batter": "SV Samson",
              "bowler": "MJ McClenaghan",
              "non_striker": "SPD Smith",
              "runs": {
                "batter": 1,
                "extras": 0,
                "total": 1
              }
            },
            {
              "batter": "SPD Smith",
              "bowler": "MJ McClenaghan",
              "non_striker": "SV Samson",
              "runs": {
                "batter": 0,
                "extras": 0,
                "total": 0
              },
              "wickets": [
                {
                  "kind": "caught",
                  "player_out": "SPD Smith",
                  "fielders": [
                    {
                      "name": "Harbhajan Singh"
                    }
                  ]
                }
              ]
            }
          ]
        },
        {
          "over": 15,
          "deliveries": [
            {
              "batter": "SV Samson",
              "bowler": "R Vinay Kumar",
              "non_striker": "KK Nair",
              "runs": {
                "batter": 1,
                "extras": 0,
                "total": 1
              }
            },
            {
              "batter": "KK Nair",
              "bowler": "R Vinay Kumar",
              "non_striker": "SV Samson",
              "runs": {
                "batter": 4,
                "extras": 0,
                "total": 4
              }
            },
            {
              "batter": "KK Nair",
              "bowler": "R Vinay Kumar",
              "non_striker": "SV Samson",
              "runs": {
                "batter": 1,
                "extras": 0,
                "total": 1
              }
            },
            {
              "batter": "SV Samson",
              "bowler": "R Vinay Kumar",
              "non_striker": "KK Nair",
              "runs": {
                "batter": 2,
                "extras": 0,
                "total": 2
              }
            },
            {
              "batter": "SV Samson",
              "bowler": "R Vinay Kumar",
              "non_striker": "KK Nair",
              "runs": {
                "batter": 4,
                "extras": 0,
                "total": 4
              }
            },
            {
              "batter": "SV Samson",
              "bowler": "R Vinay Kumar",
              "non_striker": "KK Nair",
              "runs": {
                "batter": 1,
                "extras": 0,
                "total": 1
              }
            }
          ]
        },
        {
          "over": 16,
          "deliveries": [
            {
              "batter": "SV Samson",
              "bowler": "SL Malinga",
              "non_striker": "KK Nair",
              "runs": {
                "batter": 1,
                "extras": 0,
                "total": 1
              }
            },
            {
              "batter": "KK Nair",
              "bowler": "SL Malinga",
              "extras": {
                "legbyes": 1
              },
              "non_striker": "SV Samson",
              "runs": {
                "batter": 0,
                "extras": 1,
                "total": 1
              }
            },
            {
              "batter": "SV Samson",
              "bowler": "SL Malinga",
              "non_striker": "KK Nair",
              "runs": {
                "batter": 1,
                "extras": 0,
                "total": 1
              }
            },
            {
              "batter": "KK Nair",
              "bowler": "SL Malinga",
              "non_striker": "SV Samson",
              "runs": {
                "batter": 1,
                "extras": 0,
                "total": 1
              }
            },
            {
              "batter": "SV Samson",
              "bowler": "SL Malinga",
              "non_striker": "KK Nair",
              "runs": {
                "batter": 6,
                "extras": 0,
                "total": 6
              }
            },
            {
              "batter": "SV Samson",
              "bowler": "SL Malinga",
              "non_striker": "KK Nair",
              "runs": {
                "batter": 4,
                "extras": 0,
                "total": 4
              }
            }
          ]
        },
        {
          "over": 17,
          "deliveries": [
            {
              "batter": "KK Nair",
              "bowler": "MJ McClenaghan",
              "non_striker": "SV Samson",
              "runs": {
                "batter": 1,
                "extras": 0,
                "total": 1
              }
            },
            {
              "batter": "SV Samson",
              "bowler": "MJ McClenaghan",
              "non_striker": "KK Nair",
              "runs": {
                "batter": 0,
                "extras": 0,
                "total": 0
              }
            },
            {
              "batter": "SV Samson",
              "bowler": "MJ McClenaghan",
              "non_striker": "KK Nair",
              "runs": {
                "batter": 6,
                "extras": 0,
                "total": 6
              }
            },
            {
              "batter": "SV Samson",
              "bowler": "MJ McClenaghan",
              "non_striker": "KK Nair",
              "runs": {
                "batter": 0,
                "extras": 0,
                "total": 0
              },
              "wickets": [
                {
                  "kind": "caught",
                  "player_out": "SV Samson",
                  "fielders": [
                    {
                      "name": "J Suchith"
                    }
                  ]
                }
              ]
            },
            {
              "batter": "KK Nair",
              "bowler": "MJ McClenaghan",
              "non_striker": "STR Binny",
              "runs": {
                "batter": 0,
                "extras": 0,
                "total": 0
              },
              "wickets": [
                {
                  "kind": "caught",
                  "player_out": "KK Nair",
                  "fielders": [
                    {
                      "name": "PA Patel"
                    }
                  ]
                }
              ]
            },
            {
              "batter": "DJ Hooda",
              "bowler": "MJ McClenaghan",
              "non_striker": "STR Binny",
              "runs": {
                "batter": 1,
                "extras": 0,
                "total": 1
              }
            }
          ]
        },
        {
          "over": 18,
          "deliveries": [
            {
              "batter": "DJ Hooda",
              "bowler": "SL Malinga",
              "non_striker": "STR Binny",
              "runs": {
                "batter": 0,
                "extras": 0,
                "total": 0
              },
              "wickets": [
                {
                  "kind": "caught",
                  "player_out": "DJ Hooda",
                  "fielders": [
                    {
                      "name": "UBT Chand"
                    }
                  ]
                }
              ]
            },
            {
              "batter": "STR Binny",
              "bowler": "SL Malinga",
              "non_striker": "TG Southee",
              "runs": {
                "batter": 1,
                "extras": 0,
                "total": 1
              }
            },
            {
              "batter": "TG Southee",
              "bowler": "SL Malinga",
              "non_striker": "STR Binny",
              "runs": {
                "batter": 1,
                "extras": 0,
                "total": 1
              }
            },
            {
              "batter": "STR Binny",
              "bowler": "SL Malinga",
              "non_striker": "TG Southee",
              "runs": {
                "batter": 1,
                "extras": 0,
                "total": 1
              }
            },
            {
              "batter": "TG Southee",
              "bowler": "SL Malinga",
              "non_striker": "STR Binny",
              "runs": {
                "batter": 2,
                "extras": 0,
                "total": 2
              }
            },
            {
              "batter": "TG Southee",
              "bowler": "SL Malinga",
              "non_striker": "STR Binny",
              "runs": {
                "batter": 1,
                "extras": 0,
                "total": 1
              }
            }
          ]
        },
        {
          "over": 19,
          "deliveries": [
            {
              "batter": "TG Southee",
              "bowler": "R Vinay Kumar",
              "non_striker": "STR Binny",
              "runs": {
                "batter": 1,
                "extras": 0,
                "total": 1
              }
            },
            {
              "batter": "STR Binny",
              "bowler": "R Vinay Kumar",
              "non_striker": "TG Southee",
              "runs": {
                "batter": 1,
                "extras": 0,
                "total": 1
              }
            },
            {
              "batter": "TG Southee",
              "bowler": "R Vinay Kumar",
              "non_striker": "STR Binny",
              "runs": {
                "batter": 1,
                "extras": 0,
                "total": 1
              }
            },
            {
              "batter": "STR Binny",
              "bowler": "R Vinay Kumar",
              "non_striker": "TG Southee",
              "runs": {
                "batter": 4,
                "extras": 0,
                "total": 4
              }
            },
            {
              "batter": "STR Binny",
              "bowler": "R Vinay Kumar",
              "extras": {
                "noballs": 1
              },
              "non_striker": "TG Southee",
              "runs": {
                "batter": 1,
                "extras": 1,
                "total": 2
              },
              "wickets": [
                {
                  "kind": "run out",
                  "player_out": "TG Southee",
                  "fielders": [
                    {
                      "name": "KA Pollard"
                    },
                    {
                      "name": "R Vinay Kumar"
                    }
                  ]
                }
              ]
            },
            {
              "batter": "STR Binny",
              "bowler": "R Vinay Kumar",
              "non_striker": "J Theron",
              "runs": {
                "batter": 1,
                "extras": 0,
                "total": 1
              }
            },
            {
              "batter": "J Theron",
              "bowler": "R Vinay Kumar",
              "non_striker": "STR Binny",
              "runs": {
                "batter": 1,
                "extras": 0,
                "total": 1
              }
            }
          ]
        }
      ],
      "powerplays": [
        {
          "from": 0.1,
          "to": 5.6,
          "type": "mandatory"
        }
      ],
      "target": {
        "overs": 20,
        "runs": 188
      }
    }
  ]
}